README.rst
setup.py
sluice/__init__.py
sluice/autosnapshot.py
sluice/copy.py
sluice/cull.py
sluice/sync.py
sluice.egg-info/PKG-INFO
sluice.egg-info/SOURCES.txt
sluice.egg-info/dependency_links.txt
sluice.egg-info/entry_points.txt
sluice.egg-info/requires.txt
sluice.egg-info/top_level.txt